setup.cfg
setup.py
libSpineML/__init__.py
libSpineML/smlBundle.py
libSpineML/smlComponent.py
libSpineML/smlExperiment.py
libSpineML/smlNetwork.py
libSpineML.egg-info/PKG-INFO
libSpineML.egg-info/SOURCES.txt
libSpineML.egg-info/dependency_links.txt
libSpineML.egg-info/requires.txt
libSpineML.egg-info/top_level.txt