Metadata-Version: 1.0
Name: libSpineML
Version: 0.3
Summary: Python bindings for the SpineML specifications
Home-page: http://github.com/AdamRTomkins/libSpineML
Author: Adam Tomkins
Author-email: a.tomkins@sheffield.ac.uk
License: UNKNOWN
Platform: UNKNOWN
